{
  "title": "Why did C.J. Gardner-Johnson leave the Ravens? Inside what really went down",
  "content": "Amisha Pandey has been covering the NFL since 2024, with her eyes always locked on the latest buzz — from dating rumors to Instagram posts. With a Bachelor of Commerce degree and a flair for storytelling, she mixes quirky words with an easy, consumable style that keeps readers hooked. Beyond football, Amisha dives into pop culture, viral trends, and celebrity drama, while her personal passions include music, rap, movies, and content creation. Whether it’s breaking down an NFL controversy or vibing to the latest track, she brings the same energy and curiosity to everything she does.Read More",
  "url": "https://timesofindia.indiatimes.com/sports/nfl/news/why-did-c-j-gardner-johnson-leave-the-ravens-inside-what-really-went-down/articleshow/124559436.cms",
  "scraped_timestamp": "2025-10-15T09:59:02.299454",
  "content_length": 597,
  "word_count": 97,
  "source_domain": "timesofindia.indiatimes.com"
}